tailwind/__init__.py
tailwind/apps.py
tailwind/npm.py
tailwind/utils.py
tailwind/validate.py
tailwind/app_template/cookiecutter.json
tailwind/app_template/hooks/pre_gen_project.py
tailwind/app_template/{{cookiecutter.app_name}}/__init__.py
tailwind/app_template/{{cookiecutter.app_name}}/apps.py
tailwind/app_template/{{cookiecutter.app_name}}/static_src/package.json
tailwind/app_template/{{cookiecutter.app_name}}/static_src/postcss.config.js
tailwind/app_template/{{cookiecutter.app_name}}/static_src/tailwind.config.js
tailwind/app_template/{{cookiecutter.app_name}}/static_src/src/styles.css
tailwind/app_template/{{cookiecutter.app_name}}/templates/base.html
tailwind/management/__init__.py
tailwind/management/commands/__init__.py
tailwind/management/commands/tailwind.py
tailwind/templates/tailwind/tags/css.html
tailwind/templates/tailwind/tags/preload_css.html
tailwind/templatetags/tailwind_tags.py
tailwind/templatetags/__pycache__/tailwind_tags.cpython-313.pyc
django_tailwind_4-0.1.3.dist-info/LICENSE
django_tailwind_4-0.1.3.dist-info/METADATA
django_tailwind_4-0.1.3.dist-info/WHEEL
django_tailwind_4-0.1.3.dist-info/top_level.txt
django_tailwind_4-0.1.3.dist-info/RECORD
