Metadata-Version: 2.2
Name: django-tailwind-4
Version: 0.1.3
Summary: Tailwind 4 CSS Framework for Django projects
Author-email: Ryan Sevelj <rsevs3@gmail.com>, Tim Kamanin <tim@timonweb.com>
Maintainer-email: Ryan Sevelj <rsevs3@gmail.com>
License: MIT
Project-URL: Homepage, https://github.com/rsevs3/django-tailwind-4
Project-URL: Documentation, https://django-tailwind-4.readthedocs.io
Project-URL: Tracker, https://github.com/rsevs3/django-tailwind-4/issues
Project-URL: Changelog, https://github.com/rsevs3/django-tailwind-4/releases
Keywords: django,tailwind,css
Classifier: Development Status :: 3 - Alpha
Classifier: Intended Audience :: Developers
Classifier: License :: OSI Approved :: MIT License
Classifier: Programming Language :: Python :: 3.10
Classifier: Programming Language :: Python :: 3.11
Classifier: Programming Language :: Python :: 3.12
Classifier: Operating System :: OS Independent
Classifier: Topic :: Software Development :: Libraries
Classifier: Topic :: Utilities
Classifier: Environment :: Web Environment
Classifier: Framework :: Django
Requires-Python: >=3.10.0
License-File: LICENSE
Requires-Dist: django>=3.2.14
Provides-Extra: reload
Requires-Dist: django-browser-reload>=1.17.0; extra == "reload"
Provides-Extra: dev
Requires-Dist: pytest>=8.3.4; extra == "dev"
Requires-Dist: pytest-django>=4.9.0; extra == "dev"
Requires-Dist: tox>=4.24.1; extra == "dev"
Requires-Dist: pre-commit>=4.1.0; extra == "dev"
Requires-Dist: isort>=5.13.2; extra == "dev"
Requires-Dist: flake8>=7.1.1; extra == "dev"
Requires-Dist: black>=24.10.0; extra == "dev"
Requires-Dist: Sphinx>=8.1.3; extra == "dev"
Requires-Dist: recommonmark>=0.7.1; extra == "dev"
Requires-Dist: sphinx-rtd-theme>=3.0.2; extra == "dev"
